[
  {
    "price": "RM1.6k",
    "type": "C322",
    "bedroom": "",
    "bathroom": "",
    "parking": "",
    "size": "322",
    "short": "q9x7j"
  },
  {
    "price": "390k",
    "type": "1Sty",
    "bedroom": "",
    "bathroom": "",
    "parking": "",
    "size": "332",
    "short": "e1nq2"
  },
  {
    "price": "220K",
    "type": "P321",
    "bedroom": "",
    "bathroom": "",
    "parking": "",
    "size": "321",
    "short": "k4u1x"
  },
  {
    "price": "830K",
    "type": "2Sty432",
    "bedroom": "",
    "bathroom": "",
    "parking": "",
    "size": "432",
    "short": "iva5t"
  },
  {
    "price": "300K",
    "type": "P321",
    "bedroom": "",
    "bathroom": "",
    "parking": "",
    "size": "321",
    "short": "qne9x"
  },
  {
    "price": "455K",
    "type": "1Sty321",
    "bedroom": "",
    "bathroom": "",
    "parking": "",
    "size": "321",
    "short": "tlomi"
  },
  {
    "price": "509K",
    "type": "2Sty332",
    "bedroom": "",
    "bathroom": "",
    "parking": "",
    "size": "332",
    "short": "8kgyj"
  },
  {
    "price": "150K",
    "type": "P321",
    "bedroom": "",
    "bathroom": "",
    "parking": "",
    "size": "321",
    "short": "9c2ed"
  },
  {
    "price": "890K",
    "type": "2Sty432",
    "bedroom": "",
    "bathroom": "",
    "parking": "",
    "size": "432",
    "short": "3ndkm"
  },
  {
    "price": "850K",
    "type": "2Sty432",
    "bedroom": "",
    "bathroom": "",
    "parking": "",
    "size": "432",
    "short": "4rl04"
  },
  {
    "price": "880K",
    "type": "2sty432",
    "bedroom": "",
    "bathroom": "",
    "parking": "",
    "size": "432",
    "short": "sw0oo"
  },
  {
    "price": "400K",
    "type": "1Sty",
    "bedroom": "",
    "bathroom": "",
    "parking": "",
    "size": "322",
    "short": "av8he"
  },
  {
    "price": "Pangsapuri Lagoon Perdana",
    "type": "",
    "bedroom": "",
    "bathroom": "",
    "parking": "",
    "size": "",
    "short": "oiova"
  },
  {
    "price": "210K",
    "type": "P321",
    "bedroom": "",
    "bathroom": "",
    "parking": "",
    "size": "321",
    "short": "00fli"
  },
  {
    "price": "140K",
    "type": "P32",
    "bedroom": "",
    "bathroom": "",
    "parking": "",
    "size": "32",
    "short": "d7nyo"
  },
  {
    "price": "460K",
    "type": "2Sty432",
    "bedroom": "",
    "bathroom": "",
    "parking": "",
    "size": "432",
    "short": "y293z"
  },
  {
    "price": "5000",
    "type": "3Sty562",
    "bedroom": "",
    "bathroom": "",
    "parking": "",
    "size": "562",
    "short": "o9908"
  },
  {
    "price": "200K",
    "type": "P322",
    "bedroom": "",
    "bathroom": "",
    "parking": "",
    "size": "322",
    "short": "hnzel"
  },
  {
    "price": "199K",
    "type": "P322",
    "bedroom": "",
    "bathroom": "",
    "parking": "",
    "size": "322",
    "short": "k8zp1"
  },
  {
    "price": "1100",
    "type": "P322",
    "bedroom": "",
    "bathroom": "",
    "parking": "",
    "size": "322",
    "short": "aq3yc"
  },
  {
    "price": "4500",
    "type": "2sty432",
    "bedroom": "",
    "bathroom": "",
    "parking": "",
    "size": "432",
    "short": "02an7"
  },
  {
    "price": "2.3M",
    "type": "2sty552",
    "bedroom": "",
    "bathroom": "",
    "parking": "",
    "size": "552",
    "short": "oovfp"
  },
  {
    "price": "370K",
    "type": "P322",
    "bedroom": "",
    "bathroom": "",
    "parking": "",
    "size": "322",
    "short": "05h82"
  },
  {
    "price": "2200",
    "type": "C321",
    "bedroom": "",
    "bathroom": "",
    "parking": "",
    "size": "321",
    "short": "jrara"
  },
  {
    "price": "1.32M",
    "type": "2Sty432",
    "bedroom": "",
    "bathroom": "",
    "parking": "",
    "size": "432",
    "short": "qi9f7"
  },
  {
    "price": "815K",
    "type": "2Sty432",
    "bedroom": "",
    "bathroom": "",
    "parking": "",
    "size": "432",
    "short": "2uvwi"
  },
  {
    "price": "200K",
    "type": "P321",
    "bedroom": "",
    "bathroom": "",
    "parking": "",
    "size": "321",
    "short": "xhnsr"
  },
  {
    "price": "1.28M",
    "type": "2Sty432",
    "bedroom": "",
    "bathroom": "",
    "parking": "",
    "size": "432",
    "short": "c0ykk"
  },
  {
    "price": "780k",
    "type": "2Sty322",
    "bedroom": "",
    "bathroom": "",
    "parking": "",
    "size": "322",
    "short": "xfai6"
  },
  {
    "price": "350K",
    "type": "P322",
    "bedroom": "",
    "bathroom": "",
    "parking": "",
    "size": "322",
    "short": "qkmen"
  },
  {
    "price": "Akasia A-16-01 RM 2,000",
    "type": "",
    "bedroom": "",
    "bathroom": "",
    "parking": "",
    "size": "16",
    "short": "jed1r"
  },
  {
    "price": "250K",
    "type": "P321",
    "bedroom": "",
    "bathroom": "",
    "parking": "",
    "size": "321",
    "short": "qgfjz"
  },
  {
    "price": "669K",
    "type": "2Sty432",
    "bedroom": "",
    "bathroom": "",
    "parking": "",
    "size": "432",
    "short": "bc8pb"
  },
  {
    "price": "550K",
    "type": "1",
    "bedroom": "",
    "bathroom": "",
    "parking": "",
    "size": "322",
    "short": "ibix1"
  },
  {
    "price": "1.7M",
    "type": "2Sty742",
    "bedroom": "",
    "bathroom": "",
    "parking": "",
    "size": "742",
    "short": "omf57"
  },
  {
    "price": "700K",
    "type": "2Sty332",
    "bedroom": "",
    "bathroom": "",
    "parking": "",
    "size": "332",
    "short": "dkzs5"
  },
  {
    "price": "1500",
    "type": "2Sty432",
    "bedroom": "",
    "bathroom": "",
    "parking": "",
    "size": "432",
    "short": "dtv23"
  },
  {
    "price": "1800",
    "type": "321",
    "bedroom": "",
    "bathroom": "",
    "parking": "",
    "size": "321",
    "short": "l63dp"
  },
  {
    "price": "750K",
    "type": "1",
    "bedroom": "",
    "bathroom": "",
    "parking": "",
    "size": "2",
    "short": "n5riq"
  },
  {
    "price": "680K",
    "type": "1",
    "bedroom": "",
    "bathroom": "",
    "parking": "",
    "size": "322",
    "short": "1mnx5"
  },
  {
    "price": "600K",
    "type": "2Sty",
    "bedroom": "",
    "bathroom": "",
    "parking": "",
    "size": "27",
    "short": "x6w4w"
  },
  {
    "price": "760K",
    "type": "2",
    "bedroom": "",
    "bathroom": "",
    "parking": "",
    "size": "2",
    "short": "w7hun"
  },
  {
    "price": "1.25M",
    "type": "2Sty432",
    "bedroom": "",
    "bathroom": "",
    "parking": "",
    "size": "432",
    "short": "bv79b"
  },
  {
    "price": "2800",
    "type": "Shop",
    "bedroom": "",
    "bathroom": "",
    "parking": "",
    "size": "50",
    "short": "0tvt7"
  },
  {
    "price": "670K",
    "type": "2sty432",
    "bedroom": "",
    "bathroom": "",
    "parking": "",
    "size": "",
    "short": "2pedw"
  },
  {
    "price": "290K",
    "type": "C321",
    "bedroom": "",
    "bathroom": "",
    "parking": "",
    "size": "321",
    "short": "xie01"
  },
  {
    "price": "250K",
    "type": "A221",
    "bedroom": "",
    "bathroom": "",
    "parking": "",
    "size": "221",
    "short": "ddxsd"
  },
  {
    "price": "430k",
    "type": "2sty",
    "bedroom": "",
    "bathroom": "",
    "parking": "",
    "size": "432",
    "short": "tasha"
  },
  {
    "price": "590k",
    "type": "2sty",
    "bedroom": "",
    "bathroom": "",
    "parking": "",
    "size": "422",
    "short": "l6hcn"
  },
  {
    "price": "540K",
    "type": "1",
    "bedroom": "",
    "bathroom": "",
    "parking": "",
    "size": "322",
    "short": "pdqce"
  },
  {
    "price": "750K",
    "type": "2",
    "bedroom": "",
    "bathroom": "",
    "parking": "",
    "size": "2",
    "short": "016kj"
  },
  {
    "price": "680K",
    "type": "2",
    "bedroom": "",
    "bathroom": "",
    "parking": "",
    "size": "332",
    "short": "aooda"
  },
  {
    "price": "520k-2-sty 322, 3, jalan kancung darat 28/7 Alam Megah",
    "type": "",
    "bedroom": "",
    "bathroom": "",
    "parking": "",
    "size": "2",
    "short": "zbb8u"
  },
  {
    "price": "620k",
    "type": "2H432",
    "bedroom": "",
    "bathroom": "",
    "parking": "",
    "size": "432",
    "short": "oik7v"
  },
  {
    "price": "1.05M",
    "type": "2",
    "bedroom": "",
    "bathroom": "7",
    "parking": "",
    "size": "2",
    "short": "e4sil"
  },
  {
    "price": "175k",
    "type": "P321",
    "bedroom": "",
    "bathroom": "",
    "parking": "",
    "size": "321",
    "short": "13gv6"
  },
  {
    "price": "1500",
    "type": "P321",
    "bedroom": "",
    "bathroom": "",
    "parking": "",
    "size": "321",
    "short": "50ry5"
  },
  {
    "price": "Ruby-14-F OG Heights",
    "type": "",
    "bedroom": "",
    "bathroom": "",
    "parking": "",
    "size": "14",
    "short": "7g2h1"
  },
  {
    "price": "Jalil Damai Apartments, Bukit Jalil 1st floor (Jason)",
    "type": "",
    "bedroom": "",
    "bathroom": "",
    "parking": "",
    "size": "",
    "short": "3ms3d"
  },
  {
    "price": "460K",
    "type": "1",
    "bedroom": "",
    "bathroom": "",
    "parking": "",
    "size": "1",
    "short": "st9vu"
  },
  {
    "price": "380k",
    "type": "P322",
    "bedroom": "",
    "bathroom": "",
    "parking": "",
    "size": "322",
    "short": "1p73h"
  },
  {
    "price": "310k-P322-1000 C-01-14 Harmoni",
    "type": "",
    "bedroom": "",
    "bathroom": "",
    "parking": "",
    "size": "322",
    "short": "l0wzj"
  },
  {
    "price": "1800",
    "type": "C322",
    "bedroom": "",
    "bathroom": "",
    "parking": "",
    "size": "322",
    "short": "6e9vv"
  },
  {
    "price": "Han ker texting",
    "type": "",
    "bedroom": "",
    "bathroom": "",
    "parking": "",
    "size": "",
    "short": "7enxw"
  },
  {
    "price": "360K",
    "type": "3",
    "bedroom": "",
    "bathroom": "",
    "parking": "",
    "size": "3",
    "short": "cj02g"
  },
  {
    "price": "750k",
    "type": "2",
    "bedroom": "",
    "bathroom": "",
    "parking": "",
    "size": "2",
    "short": "9u32a"
  },
  {
    "price": "345K",
    "type": "P322",
    "bedroom": "",
    "bathroom": "",
    "parking": "",
    "size": "322",
    "short": "inj8l"
  },
  {
    "price": "1400",
    "type": "P322",
    "bedroom": "",
    "bathroom": "",
    "parking": "",
    "size": "322",
    "short": "v0vj1"
  },
  {
    "price": "350K",
    "type": "P322",
    "bedroom": "",
    "bathroom": "",
    "parking": "",
    "size": "322",
    "short": "bxn50"
  },
  {
    "price": "2000",
    "type": "C322",
    "bedroom": "",
    "bathroom": "",
    "parking": "",
    "size": "322",
    "short": "p3cpt"
  },
  {
    "price": "300",
    "type": "P322",
    "bedroom": "",
    "bathroom": "",
    "parking": "",
    "size": "322",
    "short": "i01cc"
  },
  {
    "price": "315K",
    "type": "P322",
    "bedroom": "",
    "bathroom": "",
    "parking": "",
    "size": "322",
    "short": "t682q"
  },
  {
    "price": "360K",
    "type": "P322",
    "bedroom": "",
    "bathroom": "",
    "parking": "",
    "size": "322",
    "short": "gxepy"
  },
  {
    "price": "350K",
    "type": "P322",
    "bedroom": "",
    "bathroom": "",
    "parking": "",
    "size": "322",
    "short": "ztltx"
  },
  {
    "price": "630k",
    "type": "2",
    "bedroom": "",
    "bathroom": "7",
    "parking": "",
    "size": "2",
    "short": "kzops"
  },
  {
    "price": "1.5M",
    "type": "2",
    "bedroom": "",
    "bathroom": "",
    "parking": "",
    "size": "43",
    "short": "7u1le"
  },
  {
    "price": "630K",
    "type": "1",
    "bedroom": "",
    "bathroom": "",
    "parking": "",
    "size": "5",
    "short": "3zyk4"
  },
  {
    "price": "650k",
    "type": "2",
    "bedroom": "",
    "bathroom": "",
    "parking": "",
    "size": "43",
    "short": "xl6d2"
  },
  {
    "price": "750k",
    "type": "2Sty332",
    "bedroom": "",
    "bathroom": "",
    "parking": "",
    "size": "332",
    "short": "53q1f"
  },
  {
    "price": "610k",
    "type": "2",
    "bedroom": "",
    "bathroom": "",
    "parking": "",
    "size": "2",
    "short": "bmgjp"
  },
  {
    "price": "570k",
    "type": "2",
    "bedroom": "",
    "bathroom": "",
    "parking": "",
    "size": "322",
    "short": "h3jat"
  },
  {
    "price": "370k",
    "type": "P322",
    "bedroom": "",
    "bathroom": "",
    "parking": "",
    "size": "322",
    "short": "jczrj"
  },
  {
    "price": "630K",
    "type": "2",
    "bedroom": "",
    "bathroom": "",
    "parking": "",
    "size": "2",
    "short": "vypm1"
  },
  {
    "price": "1400",
    "type": "C322",
    "bedroom": "",
    "bathroom": "",
    "parking": "",
    "size": "322",
    "short": "l4zvf"
  },
  {
    "price": "650K",
    "type": "S321",
    "bedroom": "",
    "bathroom": "",
    "parking": "",
    "size": "321",
    "short": "0dq6t"
  },
  {
    "price": "The roof realty",
    "type": "",
    "bedroom": "",
    "bathroom": "",
    "parking": "",
    "size": "",
    "short": "434ki"
  },
  {
    "price": "1800",
    "type": "C322",
    "bedroom": "",
    "bathroom": "",
    "parking": "",
    "size": "322",
    "short": "gqupo"
  },
  {
    "price": "2000",
    "type": "C322",
    "bedroom": "",
    "bathroom": "",
    "parking": "",
    "size": "322",
    "short": "rnc98"
  },
  {
    "price": "330K",
    "type": "S21",
    "bedroom": "",
    "bathroom": "",
    "parking": "",
    "size": "21",
    "short": "nxojo"
  },
  {
    "price": "1800",
    "type": "S21",
    "bedroom": "",
    "bathroom": "",
    "parking": "",
    "size": "21",
    "short": "3u88w"
  },
  {
    "price": "360K",
    "type": "P322",
    "bedroom": "",
    "bathroom": "",
    "parking": "",
    "size": "322",
    "short": "gpd00"
  },
  {
    "price": "2300",
    "type": "C322",
    "bedroom": "",
    "bathroom": "",
    "parking": "",
    "size": "322",
    "short": "jdmsp"
  },
  {
    "price": "598k",
    "type": "C322",
    "bedroom": "",
    "bathroom": "",
    "parking": "",
    "size": "322",
    "short": "f85id"
  },
  {
    "price": "550K",
    "type": "C322",
    "bedroom": "",
    "bathroom": "",
    "parking": "",
    "size": "322",
    "short": "m54lf"
  },
  {
    "price": "850K",
    "type": "C322",
    "bedroom": "",
    "bathroom": "",
    "parking": "",
    "size": "322",
    "short": "nrvzk"
  },
  {
    "price": "654K",
    "type": "C322",
    "bedroom": "",
    "bathroom": "",
    "parking": "",
    "size": "322",
    "short": "2ti9e"
  },
  {
    "price": "1600",
    "type": "C322",
    "bedroom": "",
    "bathroom": "",
    "parking": "",
    "size": "322",
    "short": "qxxs9"
  },
  {
    "price": "1400",
    "type": "P322",
    "bedroom": "",
    "bathroom": "",
    "parking": "",
    "size": "322",
    "short": "g0rv8"
  },
  {
    "price": "355k",
    "type": "P322",
    "bedroom": "",
    "bathroom": "",
    "parking": "",
    "size": "322",
    "short": "if3px"
  },
  {
    "price": "343K",
    "type": "P322",
    "bedroom": "",
    "bathroom": "",
    "parking": "",
    "size": "322",
    "short": "tqc8s"
  },
  {
    "price": "350K",
    "type": "P322",
    "bedroom": "",
    "bathroom": "",
    "parking": "",
    "size": "322",
    "short": "3352t"
  },
  {
    "price": "340K",
    "type": "P322",
    "bedroom": "",
    "bathroom": "",
    "parking": "",
    "size": "322",
    "short": "4xqbt"
  },
  {
    "price": "380k",
    "type": "P322",
    "bedroom": "",
    "bathroom": "",
    "parking": "",
    "size": "322",
    "short": "tuio7"
  },
  {
    "price": "3500",
    "type": "O224",
    "bedroom": "",
    "bathroom": "",
    "parking": "",
    "size": "224",
    "short": "446jh"
  },
  {
    "price": "670k",
    "type": "T432",
    "bedroom": "",
    "bathroom": "",
    "parking": "",
    "size": "432",
    "short": "3wam9"
  },
  {
    "price": "340K",
    "type": "P322",
    "bedroom": "",
    "bathroom": "",
    "parking": "",
    "size": "322",
    "short": "97z1p"
  },
  {
    "price": "330k",
    "type": "P322",
    "bedroom": "",
    "bathroom": "",
    "parking": "",
    "size": "322",
    "short": "63g7k"
  },
  {
    "price": "400K",
    "type": "S322",
    "bedroom": "",
    "bathroom": "",
    "parking": "",
    "size": "322",
    "short": "4osn9"
  },
  {
    "price": "600k",
    "type": "2H432",
    "bedroom": "",
    "bathroom": "7",
    "parking": "",
    "size": "432",
    "short": "t3gyz"
  },
  {
    "price": "1700",
    "type": "C322",
    "bedroom": "",
    "bathroom": "",
    "parking": "",
    "size": "322",
    "short": "ion3d"
  },
  {
    "price": "1700",
    "type": "P322",
    "bedroom": "",
    "bathroom": "",
    "parking": "",
    "size": "322",
    "short": "9drce"
  },
  {
    "price": "1600",
    "type": "C322",
    "bedroom": "",
    "bathroom": "",
    "parking": "",
    "size": "322",
    "short": "hntjj"
  },
  {
    "price": "350k",
    "type": "P322",
    "bedroom": "",
    "bathroom": "",
    "parking": "",
    "size": "322",
    "short": "clldl"
  },
  {
    "price": "340K",
    "type": "P322",
    "bedroom": "",
    "bathroom": "",
    "parking": "",
    "size": "322",
    "short": "1ds94"
  },
  {
    "price": "630k",
    "type": "2H",
    "bedroom": "",
    "bathroom": "2",
    "parking": "",
    "size": "432",
    "short": "jykwx"
  },
  {
    "price": "350k",
    "type": "C321",
    "bedroom": "",
    "bathroom": "",
    "parking": "",
    "size": "321",
    "short": "pzq08"
  },
  {
    "price": "900",
    "type": "P311",
    "bedroom": "",
    "bathroom": "",
    "parking": "",
    "size": "311",
    "short": "wcmox"
  },
  {
    "price": "1600",
    "type": "P322",
    "bedroom": "",
    "bathroom": "",
    "parking": "",
    "size": "322",
    "short": "d3g4r"
  },
  {
    "price": "350K",
    "type": "P322",
    "bedroom": "",
    "bathroom": "",
    "parking": "",
    "size": "322",
    "short": "air36"
  },
  {
    "price": "330k",
    "type": "P322",
    "bedroom": "",
    "bathroom": "",
    "parking": "",
    "size": "322",
    "short": "2oui4"
  },
  {
    "price": "355k",
    "type": "P322",
    "bedroom": "",
    "bathroom": "",
    "parking": "",
    "size": "322",
    "short": "tsq3s"
  },
  {
    "price": "2200",
    "type": "C322",
    "bedroom": "",
    "bathroom": "",
    "parking": "",
    "size": "322",
    "short": "swy2z"
  },
  {
    "price": "1900",
    "type": "C322",
    "bedroom": "",
    "bathroom": "",
    "parking": "",
    "size": "322",
    "short": "l1xat"
  },
  {
    "price": "1900",
    "type": "C322",
    "bedroom": "",
    "bathroom": "",
    "parking": "",
    "size": "322",
    "short": "iinqi"
  },
  {
    "price": "485K",
    "type": "T432",
    "bedroom": "",
    "bathroom": "",
    "parking": "",
    "size": "432",
    "short": "k7wrv"
  },
  {
    "price": "700k",
    "type": "T432",
    "bedroom": "",
    "bathroom": "",
    "parking": "",
    "size": "432",
    "short": "l5r0x"
  },
  {
    "price": "610k",
    "type": "2Sty534",
    "bedroom": "",
    "bathroom": "2",
    "parking": "",
    "size": "534",
    "short": "98rlq"
  },
  {
    "price": "700k",
    "type": "432",
    "bedroom": "",
    "bathroom": "",
    "parking": "",
    "size": "432",
    "short": "rcd3n"
  },
  {
    "price": "1400",
    "type": "P322",
    "bedroom": "",
    "bathroom": "",
    "parking": "",
    "size": "322",
    "short": "pbj8x"
  },
  {
    "price": "1600",
    "type": "433",
    "bedroom": "",
    "bathroom": "",
    "parking": "",
    "size": "433",
    "short": "s2sx1"
  },
  {
    "price": "Pangsapuri Harmoni ?? ?1)",
    "type": "",
    "bedroom": "",
    "bathroom": "",
    "parking": "",
    "size": "",
    "short": "qvvvq"
  },
  {
    "price": "Pangsapuri Harmoni ?? ?2?",
    "type": "",
    "bedroom": "",
    "bathroom": "",
    "parking": "",
    "size": "",
    "short": "sjdza"
  },
  {
    "price": "350k",
    "type": "P322",
    "bedroom": "",
    "bathroom": "",
    "parking": "",
    "size": "322",
    "short": "0n5m9"
  },
  {
    "price": "295k",
    "type": "P322",
    "bedroom": "",
    "bathroom": "",
    "parking": "",
    "size": "322",
    "short": "tjdd9"
  },
  {
    "price": "1200",
    "type": "P322",
    "bedroom": "",
    "bathroom": "",
    "parking": "",
    "size": "322",
    "short": "pwdjv"
  },
  {
    "price": "2100",
    "type": "C322",
    "bedroom": "",
    "bathroom": "",
    "parking": "",
    "size": "322",
    "short": "kvbgy"
  },
  {
    "price": "145K",
    "type": "P21",
    "bedroom": "",
    "bathroom": "",
    "parking": "",
    "size": "21",
    "short": "vrdmi"
  },
  {
    "price": "550K",
    "type": "2Sty",
    "bedroom": "",
    "bathroom": "",
    "parking": "",
    "size": "422",
    "short": "uf1k3"
  },
  {
    "price": "Seksyen 9 banglor house",
    "type": "",
    "bedroom": "",
    "bathroom": "",
    "parking": "",
    "size": "",
    "short": "7ser1"
  },
  {
    "price": "355k",
    "type": "P322",
    "bedroom": "",
    "bathroom": "",
    "parking": "",
    "size": "322",
    "short": "6am8d"
  },
  {
    "price": "340K",
    "type": "P322",
    "bedroom": "",
    "bathroom": "",
    "parking": "",
    "size": "322",
    "short": "zdnpg"
  },
  {
    "price": "355k",
    "type": "S322",
    "bedroom": "",
    "bathroom": "",
    "parking": "",
    "size": "322",
    "short": "cgwrn"
  },
  {
    "price": "380k",
    "type": "S322",
    "bedroom": "",
    "bathroom": "",
    "parking": "",
    "size": "322",
    "short": "xmuj0"
  },
  {
    "price": "1600",
    "type": "C322",
    "bedroom": "",
    "bathroom": "",
    "parking": "",
    "size": "322",
    "short": "skaum"
  },
  {
    "price": "Jalan Anggerik Oncidium Kota Kemuning",
    "type": "",
    "bedroom": "",
    "bathroom": "",
    "parking": "",
    "size": "",
    "short": "qq15g"
  },
  {
    "price": "1100",
    "type": "P321",
    "bedroom": "",
    "bathroom": "",
    "parking": "",
    "size": "321",
    "short": "uf8tz"
  },
  {
    "price": "1100-2Sty422- No15, jalan 8 kajang baru, sg jelok,4300 kajang",
    "type": "",
    "bedroom": "",
    "bathroom": "",
    "parking": "",
    "size": "1100",
    "short": "w7pu8"
  },
  {
    "price": "1500",
    "type": "P321",
    "bedroom": "",
    "bathroom": "",
    "parking": "",
    "size": "321",
    "short": "r8fas"
  },
  {
    "price": "2400",
    "type": "C322",
    "bedroom": "",
    "bathroom": "",
    "parking": "",
    "size": "322",
    "short": "3zga4"
  },
  {
    "price": "3000",
    "type": "C322",
    "bedroom": "",
    "bathroom": "",
    "parking": "",
    "size": "322",
    "short": "30abi"
  },
  {
    "price": "2000",
    "type": "c322",
    "bedroom": "",
    "bathroom": "",
    "parking": "",
    "size": "322",
    "short": "ddjz1"
  },
  {
    "price": "2200",
    "type": "C322",
    "bedroom": "",
    "bathroom": "",
    "parking": "",
    "size": "1",
    "short": "ejy31"
  },
  {
    "price": "2300",
    "type": "C322",
    "bedroom": "",
    "bathroom": "",
    "parking": "",
    "size": "322",
    "short": "z6okw"
  },
  {
    "price": "2100",
    "type": "C221",
    "bedroom": "",
    "bathroom": "",
    "parking": "",
    "size": "221",
    "short": "6nek1"
  },
  {
    "price": "2000",
    "type": "C423",
    "bedroom": "",
    "bathroom": "",
    "parking": "",
    "size": "423",
    "short": "a7u9w"
  },
  {
    "price": "2800",
    "type": "C422",
    "bedroom": "",
    "bathroom": "",
    "parking": "",
    "size": "422",
    "short": "cnrpg"
  },
  {
    "price": "1600",
    "type": "P321",
    "bedroom": "",
    "bathroom": "",
    "parking": "",
    "size": "321",
    "short": "zhtbl"
  },
  {
    "price": "1500",
    "type": "P321",
    "bedroom": "",
    "bathroom": "",
    "parking": "",
    "size": "321",
    "short": "l0c3c"
  },
  {
    "price": "Mercu jalil",
    "type": "",
    "bedroom": "",
    "bathroom": "",
    "parking": "",
    "size": "",
    "short": "vk096"
  },
  {
    "price": "1600-P322-1000 A-19-15 Mercu Jalil",
    "type": "",
    "bedroom": "",
    "bathroom": "",
    "parking": "",
    "size": "1600",
    "short": "y0vn2"
  },
  {
    "price": "1900-P322-1200 A-16 Akasia",
    "type": "",
    "bedroom": "",
    "bathroom": "",
    "parking": "",
    "size": "1900",
    "short": "591w2"
  },
  {
    "price": "1400",
    "type": "P322",
    "bedroom": "",
    "bathroom": "",
    "parking": "",
    "size": "322",
    "short": "hahdy"
  },
  {
    "price": "2100",
    "type": "C332",
    "bedroom": "",
    "bathroom": "",
    "parking": "",
    "size": "332",
    "short": "hgvaf"
  },
  {
    "price": "1700",
    "type": "C322",
    "bedroom": "",
    "bathroom": "",
    "parking": "",
    "size": "322",
    "short": "kxtec"
  },
  {
    "price": "1800",
    "type": "C322",
    "bedroom": "",
    "bathroom": "",
    "parking": "",
    "size": "322",
    "short": "mxxpe"
  },
  {
    "price": "1700",
    "type": "C322",
    "bedroom": "",
    "bathroom": "",
    "parking": "",
    "size": "322",
    "short": "buo0i"
  },
  {
    "price": "2400",
    "type": "C332",
    "bedroom": "",
    "bathroom": "",
    "parking": "",
    "size": "16",
    "short": "hlupi"
  },
  {
    "price": "1600",
    "type": "C322",
    "bedroom": "",
    "bathroom": "",
    "parking": "",
    "size": "322",
    "short": "8d2eg"
  },
  {
    "price": "300k",
    "type": "P322",
    "bedroom": "",
    "bathroom": "",
    "parking": "",
    "size": "322",
    "short": "qppfy"
  },
  {
    "price": "380k",
    "type": "P322",
    "bedroom": "",
    "bathroom": "",
    "parking": "",
    "size": "322",
    "short": "faqgt"
  },
  {
    "price": "2700",
    "type": "C422",
    "bedroom": "",
    "bathroom": "",
    "parking": "",
    "size": "422",
    "short": "mc3lt"
  },
  {
    "price": "560",
    "type": "C322",
    "bedroom": "",
    "bathroom": "",
    "parking": "",
    "size": "322",
    "short": "j62cz"
  },
  {
    "price": "350k",
    "type": "P322",
    "bedroom": "",
    "bathroom": "",
    "parking": "",
    "size": "322",
    "short": "ka6is"
  },
  {
    "price": "550k",
    "type": "C322",
    "bedroom": "",
    "bathroom": "",
    "parking": "",
    "size": "322",
    "short": "btz4q"
  },
  {
    "price": "130K",
    "type": "P321",
    "bedroom": "",
    "bathroom": "",
    "parking": "",
    "size": "321",
    "short": "8zjd8"
  },
  {
    "price": "2400",
    "type": "C322",
    "bedroom": "",
    "bathroom": "",
    "parking": "",
    "size": "322",
    "short": "rvoe4"
  },
  {
    "price": "1200",
    "type": "P322",
    "bedroom": "",
    "bathroom": "",
    "parking": "",
    "size": "322",
    "short": "8pv2x"
  },
  {
    "price": "1200",
    "type": "P322",
    "bedroom": "",
    "bathroom": "",
    "parking": "",
    "size": "322",
    "short": "2iev8"
  },
  {
    "price": "Hamoni",
    "type": "",
    "bedroom": "",
    "bathroom": "",
    "parking": "",
    "size": "",
    "short": "itk1m"
  },
  {
    "price": "360k",
    "type": "P322",
    "bedroom": "",
    "bathroom": "",
    "parking": "",
    "size": "322",
    "short": "nk83u"
  },
  {
    "price": "1500",
    "type": "C322",
    "bedroom": "",
    "bathroom": "",
    "parking": "",
    "size": "322",
    "short": "qbp9t"
  },
  {
    "price": "950k",
    "type": "D43",
    "bedroom": "",
    "bathroom": "",
    "parking": "",
    "size": "",
    "short": "tdh6p"
  },
  {
    "price": "1500",
    "type": "322",
    "bedroom": "",
    "bathroom": "",
    "parking": "",
    "size": "322",
    "short": "qnz65"
  },
  {
    "price": "1500",
    "type": "C322",
    "bedroom": "",
    "bathroom": "",
    "parking": "",
    "size": "322",
    "short": "xn3ih"
  },
  {
    "price": "350k",
    "type": "S322",
    "bedroom": "",
    "bathroom": "",
    "parking": "",
    "size": "322",
    "short": "cqhzq"
  },
  {
    "price": "380K",
    "type": "S322",
    "bedroom": "",
    "bathroom": "",
    "parking": "",
    "size": "322",
    "short": "t0e6w"
  },
  {
    "price": "368K",
    "type": "P322",
    "bedroom": "",
    "bathroom": "",
    "parking": "",
    "size": "322",
    "short": "qu5ym"
  },
  {
    "price": "400K",
    "type": "S322",
    "bedroom": "",
    "bathroom": "",
    "parking": "",
    "size": "322",
    "short": "rn2qr"
  },
  {
    "price": "Akasia Condo B8-12 FF RM2K",
    "type": "",
    "bedroom": "",
    "bathroom": "",
    "parking": "",
    "size": "8",
    "short": "sleh1"
  },
  {
    "price": "2000",
    "type": "C322",
    "bedroom": "",
    "bathroom": "",
    "parking": "",
    "size": "322",
    "short": "x4v2y"
  },
  {
    "price": "Cover Photo-20240824T153938Z-001",
    "type": "",
    "bedroom": "",
    "bathroom": "",
    "parking": "",
    "size": "",
    "short": "9008f"
  },
  {
    "price": "130k",
    "type": "P311",
    "bedroom": "",
    "bathroom": "",
    "parking": "",
    "size": "311",
    "short": "m434p"
  },
  {
    "price": "230k",
    "type": "C321",
    "bedroom": "",
    "bathroom": "",
    "parking": "",
    "size": "321",
    "short": "p8cr9"
  },
  {
    "price": "360K",
    "type": "P322",
    "bedroom": "",
    "bathroom": "",
    "parking": "",
    "size": "322",
    "short": "e53pw"
  },
  {
    "price": "Harmoni 295k",
    "type": "",
    "bedroom": "",
    "bathroom": "",
    "parking": "",
    "size": "",
    "short": "19bay"
  },
  {
    "price": "Akasia Block A 1800",
    "type": "",
    "bedroom": "",
    "bathroom": "",
    "parking": "",
    "size": "",
    "short": "wzup6"
  },
  {
    "price": "1600",
    "type": "C322",
    "bedroom": "",
    "bathroom": "",
    "parking": "",
    "size": "322",
    "short": "bsl9b"
  },
  {
    "price": "1550",
    "type": "C322",
    "bedroom": "",
    "bathroom": "",
    "parking": "",
    "size": "322",
    "short": "53w8j"
  },
  {
    "price": "Custom Office Templates",
    "type": "",
    "bedroom": "",
    "bathroom": "",
    "parking": "",
    "size": "",
    "short": "unm9l"
  },
  {
    "price": "1300",
    "type": "C111",
    "bedroom": "",
    "bathroom": "",
    "parking": "",
    "size": "111",
    "short": "o85z9"
  },
  {
    "price": "130k",
    "type": "P221",
    "bedroom": "",
    "bathroom": "",
    "parking": "",
    "size": "221",
    "short": "rqpns"
  },
  {
    "price": "2100",
    "type": "C322",
    "bedroom": "",
    "bathroom": "",
    "parking": "",
    "size": "322",
    "short": "0lpur"
  },
  {
    "price": "520k",
    "type": "C322",
    "bedroom": "",
    "bathroom": "",
    "parking": "",
    "size": "322",
    "short": "4j4i2"
  },
  {
    "price": "400k",
    "type": "S322",
    "bedroom": "",
    "bathroom": "",
    "parking": "",
    "size": "322",
    "short": "qnj5h"
  },
  {
    "price": "600k",
    "type": "S322",
    "bedroom": "",
    "bathroom": "",
    "parking": "",
    "size": "322",
    "short": "arf6g"
  },
  {
    "price": "480k",
    "type": "S322",
    "bedroom": "",
    "bathroom": "",
    "parking": "",
    "size": "322",
    "short": "8py51"
  },
  {
    "price": "229k",
    "type": "S32",
    "bedroom": "",
    "bathroom": "",
    "parking": "",
    "size": "32",
    "short": "d3wco"
  },
  {
    "price": "140k",
    "type": "P221",
    "bedroom": "",
    "bathroom": "",
    "parking": "",
    "size": "221",
    "short": "188q4"
  },
  {
    "price": "480k",
    "type": "C322",
    "bedroom": "",
    "bathroom": "",
    "parking": "",
    "size": "322",
    "short": "sq1vh"
  },
  {
    "price": "380k",
    "type": "C322",
    "bedroom": "",
    "bathroom": "",
    "parking": "",
    "size": "322",
    "short": "5towg"
  },
  {
    "price": "1600",
    "type": "C422",
    "bedroom": "",
    "bathroom": "",
    "parking": "",
    "size": "422",
    "short": "d46al"
  },
  {
    "price": "580k",
    "type": "C322",
    "bedroom": "",
    "bathroom": "",
    "parking": "",
    "size": "322",
    "short": "u4392"
  },
  {
    "price": "250k",
    "type": "P112",
    "bedroom": "",
    "bathroom": "",
    "parking": "",
    "size": "112",
    "short": "gu4ds"
  },
  {
    "price": "600k",
    "type": "C332",
    "bedroom": "",
    "bathroom": "",
    "parking": "",
    "size": "332",
    "short": "0cnbe"
  },
  {
    "price": "539k",
    "type": "C322",
    "bedroom": "",
    "bathroom": "",
    "parking": "",
    "size": "322",
    "short": "c3edh"
  },
  {
    "price": "Aman Jalil Basic Unit Picture Sample",
    "type": "",
    "bedroom": "",
    "bathroom": "",
    "parking": "",
    "size": "",
    "short": "hwsec"
  },
  {
    "price": "Akasia Rm 1600",
    "type": "",
    "bedroom": "",
    "bathroom": "",
    "parking": "",
    "size": "",
    "short": "8a2vh"
  },
  {
    "price": "The Harve B-20 Rm2300",
    "type": "",
    "bedroom": "",
    "bathroom": "",
    "parking": "",
    "size": "",
    "short": "ajver"
  },
  {
    "price": "Condominum bukit OUG 1.3k",
    "type": "",
    "bedroom": "",
    "bathroom": "",
    "parking": "",
    "size": "",
    "short": "8ad2r"
  },
  {
    "price": "Putra Indah @ Putra Heights",
    "type": "",
    "bedroom": "",
    "bathroom": "",
    "parking": "",
    "size": "",
    "short": "gsmoh"
  },
  {
    "price": "Harmoni Rent 1200",
    "type": "",
    "bedroom": "",
    "bathroom": "",
    "parking": "",
    "size": "",
    "short": "4uyyz"
  },
  {
    "price": "Harmoni Rent RM 1400",
    "type": "",
    "bedroom": "",
    "bathroom": "",
    "parking": "",
    "size": "",
    "short": "dju28"
  },
  {
    "price": "2 Sty Putra bahagia 1650 putra height",
    "type": "",
    "bedroom": "",
    "bathroom": "",
    "parking": "",
    "size": "",
    "short": "ub5u7"
  },
  {
    "price": "Aman Jalil RM 1.4k PF",
    "type": "",
    "bedroom": "",
    "bathroom": "",
    "parking": "",
    "size": "",
    "short": "85hc8"
  },
  {
    "price": "Alam Sanjung Serviced Apartment",
    "type": "",
    "bedroom": "",
    "bathroom": "",
    "parking": "",
    "size": "",
    "short": "rs65w"
  },
  {
    "price": "Seri Ixora, Seksyen 27  S 285k",
    "type": "",
    "bedroom": "",
    "bathroom": "",
    "parking": "",
    "size": "",
    "short": "sgy8u"
  },
  {
    "price": "R  Putra Permai Putra Heights",
    "type": "",
    "bedroom": "",
    "bathroom": "",
    "parking": "",
    "size": "",
    "short": "zmjh4"
  },
  {
    "price": "2-storey Intermediate Unit at PUJ2",
    "type": "",
    "bedroom": "",
    "bathroom": "",
    "parking": "",
    "size": "2",
    "short": "b5euc"
  },
  {
    "price": "Aroma Tropika, Shah Alam",
    "type": "",
    "bedroom": "",
    "bathroom": "",
    "parking": "",
    "size": "",
    "short": "ywdde"
  },
  {
    "price": "Putra Permai (Putra Heights)",
    "type": "",
    "bedroom": "",
    "bathroom": "",
    "parking": "",
    "size": "",
    "short": "88i7o"
  },
  {
    "price": "Putra Indah @ Putra Heights, Subang Jaya Rm 2700",
    "type": "",
    "bedroom": "",
    "bathroom": "",
    "parking": "",
    "size": "",
    "short": "veg3z"
  },
  {
    "price": "The Wharf @ puchong",
    "type": "",
    "bedroom": "",
    "bathroom": "",
    "parking": "",
    "size": "",
    "short": "n9su8"
  },
  {
    "price": "2 Sty House at U10 Shah Alam Rm 2,000",
    "type": "",
    "bedroom": "",
    "bathroom": "",
    "parking": "",
    "size": "",
    "short": "yliq8"
  },
  {
    "price": "Pangsapuri Lotus (Teratai) Rm 1150",
    "type": "",
    "bedroom": "",
    "bathroom": "",
    "parking": "",
    "size": "",
    "short": "5ngjm"
  },
  {
    "price": "Sri cempaka apt puchong Rm 1,200",
    "type": "",
    "bedroom": "",
    "bathroom": "",
    "parking": "",
    "size": "",
    "short": "6ran8"
  },
  {
    "price": "1 Sty Bsp suajana",
    "type": "",
    "bedroom": "",
    "bathroom": "",
    "parking": "",
    "size": "",
    "short": "vlk0x"
  },
  {
    "price": "Flat PKNS Seksyen 7 Shah Alam RM 1250",
    "type": "",
    "bedroom": "",
    "bathroom": "",
    "parking": "",
    "size": "",
    "short": "zdafo"
  },
  {
    "price": "Sri Kemuning",
    "type": "",
    "bedroom": "",
    "bathroom": "",
    "parking": "",
    "size": "",
    "short": "z8j3v"
  },
  {
    "price": "Akasia Rm1600 Simom",
    "type": "",
    "bedroom": "",
    "bathroom": "",
    "parking": "",
    "size": "",
    "short": "fquww"
  },
  {
    "price": "Ivory kajang Rm 1,300",
    "type": "",
    "bedroom": "",
    "bathroom": "",
    "parking": "",
    "size": "",
    "short": "gdzds"
  },
  {
    "price": "BSP SP1 2sty Rm 1750",
    "type": "",
    "bedroom": "",
    "bathroom": "",
    "parking": "",
    "size": "",
    "short": "z8j01"
  },
  {
    "price": "Green Avanue BJ Rm1700",
    "type": "",
    "bedroom": "",
    "bathroom": "",
    "parking": "",
    "size": "",
    "short": "gr2fi"
  },
  {
    "price": "Bsp 1-Sty rent",
    "type": "",
    "bedroom": "",
    "bathroom": "",
    "parking": "",
    "size": "1",
    "short": "1cuib"
  },
  {
    "price": "BSP Skypark 1.4k Devon",
    "type": "",
    "bedroom": "",
    "bathroom": "",
    "parking": "",
    "size": "",
    "short": "i9q0u"
  },
  {
    "price": "Jalil Damai Rm 1,600",
    "type": "",
    "bedroom": "",
    "bathroom": "",
    "parking": "",
    "size": "",
    "short": "1a4sy"
  },
  {
    "price": "E-tiara FF Rm1,900",
    "type": "",
    "bedroom": "",
    "bathroom": "",
    "parking": "",
    "size": "",
    "short": "whds8"
  },
  {
    "price": "Offer Lot USJ",
    "type": "",
    "bedroom": "",
    "bathroom": "",
    "parking": "",
    "size": "",
    "short": "c0qff"
  },
  {
    "price": "I soho- I city R RM 1,700",
    "type": "",
    "bedroom": "",
    "bathroom": "",
    "parking": "",
    "size": "",
    "short": "45h3x"
  },
  {
    "price": "Warehouse @ padang jawa",
    "type": "",
    "bedroom": "",
    "bathroom": "",
    "parking": "",
    "size": "",
    "short": "uu2c9"
  },
  {
    "price": "Sky impiamna condo",
    "type": "",
    "bedroom": "",
    "bathroom": "",
    "parking": "",
    "size": "",
    "short": "ygag3"
  },
  {
    "price": "Menara Suria V12 Sovo Subang jaya",
    "type": "",
    "bedroom": "",
    "bathroom": "",
    "parking": "",
    "size": "",
    "short": "a871d"
  },
  {
    "price": "USJ 14 2Sty R Rm 1,700",
    "type": "",
    "bedroom": "",
    "bathroom": "",
    "parking": "",
    "size": "",
    "short": "p9c34"
  },
  {
    "price": "Pangsapuri Jaya TTDI Jaya Rm 1,500",
    "type": "",
    "bedroom": "",
    "bathroom": "",
    "parking": "",
    "size": "",
    "short": "vqh3a"
  },
  {
    "price": "Pangsapuri damai Seksyen 27 shah alam",
    "type": "",
    "bedroom": "",
    "bathroom": "",
    "parking": "",
    "size": "",
    "short": "t5vq9"
  },
  {
    "price": "Baiduri apartment",
    "type": "",
    "bedroom": "",
    "bathroom": "",
    "parking": "",
    "size": "",
    "short": "5cxlj"
  },
  {
    "price": "Jall Mas",
    "type": "",
    "bedroom": "",
    "bathroom": "",
    "parking": "",
    "size": "",
    "short": "dc1b4"
  },
  {
    "price": "Casa tiara RM 1700",
    "type": "",
    "bedroom": "",
    "bathroom": "",
    "parking": "",
    "size": "",
    "short": "3q06c"
  },
  {
    "price": "Akasia Block B RM 1,500",
    "type": "",
    "bedroom": "",
    "bathroom": "",
    "parking": "",
    "size": "",
    "short": "otdyy"
  },
  {
    "price": "Hana 16-02",
    "type": "",
    "bedroom": "",
    "bathroom": "",
    "parking": "",
    "size": "16",
    "short": "69w08"
  },
  {
    "price": "Nobeille House",
    "type": "",
    "bedroom": "",
    "bathroom": "",
    "parking": "",
    "size": "",
    "short": "89ptj"
  },
  {
    "price": "Goodyear court 2 Rm 1,400",
    "type": "",
    "bedroom": "",
    "bathroom": "",
    "parking": "",
    "size": "",
    "short": "mr1pl"
  },
  {
    "price": "Paradesa Rustica Condo",
    "type": "",
    "bedroom": "",
    "bathroom": "",
    "parking": "",
    "size": "",
    "short": "ixev9"
  },
  {
    "price": "Shaftsbury Residence Cyberjaya Rm 1,100",
    "type": "",
    "bedroom": "",
    "bathroom": "",
    "parking": "",
    "size": "",
    "short": "0gvwg"
  },
  {
    "price": "PPA1M",
    "type": "",
    "bedroom": "",
    "bathroom": "",
    "parking": "",
    "size": "",
    "short": "1p2b5"
  },
  {
    "price": "Arena Green Rm 1000",
    "type": "",
    "bedroom": "",
    "bathroom": "",
    "parking": "",
    "size": "",
    "short": "rbh2m"
  },
  {
    "price": "Aman jalil P F RM 1300",
    "type": "",
    "bedroom": "",
    "bathroom": "",
    "parking": "",
    "size": "",
    "short": "pjdvw"
  },
  {
    "price": "The Havre Bukit Jalil Rm 2000",
    "type": "",
    "bedroom": "",
    "bathroom": "",
    "parking": "",
    "size": "",
    "short": "jtszo"
  },
  {
    "price": "Kenwingston Avenue",
    "type": "",
    "bedroom": "",
    "bathroom": "",
    "parking": "",
    "size": "",
    "short": "lay2i"
  },
  {
    "price": "Sri Rakyat Apartment 1350",
    "type": "",
    "bedroom": "",
    "bathroom": "",
    "parking": "",
    "size": "",
    "short": "553wc"
  },
  {
    "price": "Mercu Jalil F F RM 1700",
    "type": "",
    "bedroom": "",
    "bathroom": "",
    "parking": "",
    "size": "",
    "short": "b0rrm"
  },
  {
    "price": "Aman Jallil P F Rm 1400",
    "type": "",
    "bedroom": "",
    "bathroom": "",
    "parking": "",
    "size": "",
    "short": "qu17l"
  },
  {
    "price": "Vista Komanwel A",
    "type": "",
    "bedroom": "",
    "bathroom": "",
    "parking": "",
    "size": "",
    "short": "8llp3"
  },
  {
    "price": "Aman Jalil",
    "type": "",
    "bedroom": "",
    "bathroom": "",
    "parking": "",
    "size": "",
    "short": "f358r"
  },
  {
    "price": "Parkhill Rm 2,800",
    "type": "",
    "bedroom": "",
    "bathroom": "",
    "parking": "",
    "size": "",
    "short": "1bf4q"
  },
  {
    "price": "Solstice @ Pan'gaea",
    "type": "",
    "bedroom": "",
    "bathroom": "",
    "parking": "",
    "size": "",
    "short": "tx8n2"
  },
  {
    "price": "The jalil",
    "type": "",
    "bedroom": "",
    "bathroom": "",
    "parking": "",
    "size": "",
    "short": "gyr6t"
  },
  {
    "price": "Suajana sp7",
    "type": "",
    "bedroom": "",
    "bathroom": "",
    "parking": "",
    "size": "",
    "short": "3b1ga"
  }
]